README.md
setup.py
dnrlib/__init__.py
dnrlib/class_dnr.py
dnrlib/class_neural.py
dnrlib.egg-info/PKG-INFO
dnrlib.egg-info/SOURCES.txt
dnrlib.egg-info/dependency_links.txt
dnrlib.egg-info/not-zip-safe
dnrlib.egg-info/requires.txt
dnrlib.egg-info/top_level.txt