Metadata-Version: 1.0
Name: dnrlib
Version: 0.1
Summary: Deep Node Ranking
Home-page: https://github.com/skblaz/DNR
Author: Blaž Škrlj
Author-email: blaz.skrlj@ijs.si
License: bsd-3-clause-clear
Platform: UNKNOWN
